{"styles": [{"id": "japan_landuse_labels", "extends": "landuse_points", "styleSet": "tilezen_points", "when": ["==", ["get", "source"], "ipc"], "technique": "text", "description": "Landuse Labels", "category": "small-land-use-labels", "minZoomLevel": ["case", ["ref", "Is.Commercial"], 12, ["ref", "Is.Industrial"], 12, ["ref", "Is.ImperialFacility"], 12, ["ref", "Is.InstitutionalOffice"], 12, ["ref", "Is.Cemetery"], 13, ["ref", "Is.Hospital"], 13, ["ref", "Is.University"], 13, ["ref", "Is.RailwayStation"], 13, ["ref", "Is.Retail"], 13, ["ref", "Is.ServiceArea"], 13, ["ref", "Is.Transportation"], 13, ["ref", "Is.PlaceOfWorship"], 13, ["ref", "Is.Attraction.Park"], 13, ["ref", "Is.AccommodationFacility"], 13, ["ref", "Is.OutdoorFacility"], 13, ["ref", "Is.School"], 14, ["ref", "Is.Dam"], 15, ["ref", "Is.Block"], 15, ["ref", "Is.Sand"], 15, ["ref", "Is.Grass"], 15, ["ref", "Is.Grassland"], 15, ["ref", "Is.Pedestrian"], 15, ["ref", "Is.RoadRestrictedArea"], 15, ["ref", "Is.Steps"], 15, ["ref", "Is.Divider"], 15, ["ref", "Is.Railyard"], 15, ["ref", "Is.PavedArea"], 15, ["ref", "Is.Breakwater"], 15, ["ref", "Is.UndergroundCity"], 15, null], "attr": {"outline-size": ["case", ["any", ["ref", "Is.PlaceOfWorship"], ["ref", "Is.Attraction.Park"], ["ref", "Is.ImperialFacility"]], ["ppi-scale", ["ref", "ParkInfo.FontStyle.OutlineWidth"], ["ref", "ScalePpi.labels"]], ["ref", "Is.School"], ["ppi-scale", ["ref", "UniversityCampusInfo.FontStyle.OutlineWidth"], ["ref", "ScalePpi.labels"]], ["ref", "Is.Dam"], ["ppi-scale", ["ref", "DamInfo.FontStyle.OutlineWidth"], ["ref", "ScalePpi.labels"]], ["any", ["ref", "Is.AccommodationFacility"], ["ref", "Is.OutdoorFacility"]], ["ppi-scale", ["ref", "CemeteryInfo.FontStyle.OutlineWidth"], ["ref", "ScalePpi.labels"]], ["ref", "Is.InstitutionalOffice"], ["ppi-scale", ["ref", "InstitutionalOfficeInfo.FontStyle.OutlineWidth"], ["ref", "ScalePpi.labels"]], ["any", ["ref", "Is.Retail"], ["ref", "Is.ServiceArea"], ["ref", "Is.Transportation"]], ["ppi-scale", ["ref", "IndustrialComplexInfo.FontStyle.OutlineWidth"], ["ref", "ScalePpi.labels"]], ["ref", "Is.Wetland"], ["ppi-scale", ["ref", "WetlandInfo.FontStyle.OutlineWidth"], ["ref", "ScalePpi.labels"]], ["base-attribute-value"]], "outline-color": ["case", ["any", ["ref", "Is.PlaceOfWorship"], ["ref", "Is.Attraction.Park"], ["ref", "Is.ImperialFacility"]], ["ref", "ParkInfo.FontStyle.OutlineColor"], ["ref", "Is.School"], ["ref", "UniversityCampusInfo.FontStyle.OutlineColor"], ["ref", "Is.Dam"], ["ref", "DamInfo.FontStyle.OutlineColor"], ["any", ["ref", "Is.AccommodationFacility"], ["ref", "Is.OutdoorFacility"]], ["ref", "CemeteryInfo.FontStyle.OutlineColor"], ["ref", "Is.InstitutionalOffice"], ["ref", "InstitutionalOfficeInfo.FontStyle.OutlineColor"], ["any", ["ref", "Is.Retail"], ["ref", "Is.ServiceArea"], ["ref", "Is.Transportation"]], ["ref", "IndustrialComplexInfo.FontStyle.OutlineColor"], ["ref", "Is.Wetland"], ["ref", "WetlandInfo.FontStyle.OutlineColor"], ["base-attribute-value"]], "color": ["case", ["any", ["ref", "Is.PlaceOfWorship"], ["ref", "Is.Attraction.Park"], ["ref", "Is.ImperialFacility"]], ["ref", "ParkInfo.FontStyle.Color"], ["ref", "Is.School"], ["ref", "UniversityCampusInfo.FontStyle.Color"], ["ref", "Is.Dam"], ["ref", "DamInfo.FontStyle.Color"], ["any", ["ref", "Is.AccommodationFacility"], ["ref", "Is.OutdoorFacility"]], ["ref", "CemeteryInfo.FontStyle.Color"], ["ref", "Is.InstitutionalOffice"], ["ref", "InstitutionalOfficeInfo.FontStyle.Color"], ["any", ["ref", "Is.Retail"], ["ref", "Is.ServiceArea"], ["ref", "Is.Transportation"]], ["ref", "IndustrialComplexInfo.FontStyle.Color"], ["ref", "Is.Wetland"], ["ref", "WetlandInfo.FontStyle.Color"], ["base-attribute-value"]], "size": ["case", ["any", ["ref", "Is.PlaceOfWorship"], ["ref", "Is.Attraction.Park"], ["ref", "Is.ImperialFacility"]], ["ppi-scale", ["ref", "ParkInfo.FontStyle.Size"], ["ref", "ScalePpi.labels"]], ["ref", "Is.School"], ["ppi-scale", ["ref", "UniversityCampusInfo.FontStyle.Size"], ["ref", "ScalePpi.labels"]], ["ref", "Is.Dam"], ["ppi-scale", ["ref", "DamInfo.FontStyle.Size"], ["ref", "ScalePpi.labels"]], ["any", ["ref", "Is.AccommodationFacility"], ["ref", "Is.OutdoorFacility"]], ["ppi-scale", ["ref", "CemeteryInfo.FontStyle.Size"], ["ref", "ScalePpi.labels"]], ["ref", "Is.InstitutionalOffice"], ["ppi-scale", ["ref", "InstitutionalOfficeInfo.FontStyle.Size"], ["ref", "ScalePpi.labels"]], ["any", ["ref", "Is.Retail"], ["ref", "Is.ServiceArea"], ["ref", "Is.Transportation"]], ["ppi-scale", ["ref", "IndustrialComplexInfo.FontStyle.Size"], ["ref", "ScalePpi.labels"]], ["ref", "Is.Wetland"], 0, ["any", ["ref", "Is.RailwayStation"], ["ref", "Is.CommuterStation"]], 0, ["base-attribute-value"]], "shape": "point"}}, {"id": "japan_landuse_polygons", "extends": "landuse_polygon", "styleSet": "tilezen_polygons", "when": ["==", ["get", "source"], "ipc"], "technique": "polygon", "description": "Landuse Polygons", "minZoomLevel": ["case", ["ref", "Is.Commercial"], 12, ["ref", "Is.Industrial"], 12, ["ref", "Is.ImperialFacility"], 12, ["ref", "Is.InstitutionalOffice"], 12, ["ref", "Is.Cemetery"], 13, ["ref", "Is.Hospital"], 13, ["ref", "Is.University"], 13, ["ref", "Is.RailwayStation"], 13, ["ref", "Is.Retail"], 13, ["ref", "Is.ServiceArea"], 13, ["ref", "Is.Transportation"], 13, ["ref", "Is.PlaceOfWorship"], 13, ["ref", "Is.Attraction.Park"], 13, ["ref", "Is.AccommodationFacility"], 13, ["ref", "Is.OutdoorFacility"], 13, ["ref", "Is.School"], 14, ["ref", "Is.Dam"], 15, ["ref", "Is.Block"], 15, ["ref", "Is.Sand"], 15, ["ref", "Is.Grass"], 15, ["ref", "Is.Grassland"], 15, ["ref", "Is.Pedestrian"], 15, ["ref", "Is.RoadRestrictedArea"], 15, ["ref", "Is.Steps"], 15, ["ref", "Is.Divider"], 15, ["ref", "Is.Railyard"], 15, ["ref", "Is.PavedArea"], 15, ["ref", "Is.Breakwater"], 15, ["ref", "Is.UndergroundCity"], 15, null], "category": ["case", ["ref", "Is.Grassland"], "grassland", ["ref", "Is.Grass"], "grass", ["ref", "Is.FloodProneArea"], "flood_prone_area", ["ref", "Is.Block"], "block", ["ref", "Is.RoadRestrictedArea"], "restricted_road", ["ref", "Is.Steps"], "steps", ["ref", "Is.PavedArea"], "paved_area", ["ref", "Is.Pedestrian"], "japan-pedestrian", ["ref", "Is.Sand"], "sand", ["ref", "Is.UndergroundCity"], "underground_area", ["ref", "Is.Divider"], "divider", ["ref", "Is.PlaceOfWorship"], "worship_place", ["ref", "Is.School"], "school", ["ref", "Is.Wetland"], "wetland", ["ref", "Is.Breakwater"], "breakwater", ["ref", "Is.AccommodationFacility"], "accomodation_facility", ["ref", "Is.Attraction.Park"], "attraction", ["ref", "Is.Dam"], "dam", ["ref", "Is.ImperialFacility"], "imperial_facility", ["ref", "Is.InstitutionalOffice"], "institutional_office", ["ref", "Is.OutdoorFacility"], "outdoor_facility", ["ref", "Is.Pool"], "pool", ["ref", "Is.Retail"], "retail", ["ref", "Is.ServiceArea"], "service_area", ["ref", "Is.Transportation"], "transportation", ["ref", "Is.TunnelEntrance"], "tunnel_entrance", ["ref", "Is.RailwayStation"], "railway_station", ["ref", "Is.CommuterStation"], "commuter_station", ["base-attribute-value"]], "attr": {"color": ["case", ["ref", "Is.Grassland"], ["ref", "Grassland.Color"], ["ref", "Is.Grass"], ["ref", "Grass.Color"], ["ref", "Is.FloodProneArea"], ["ref", "FloodProneArea.Color"], ["ref", "Is.Block"], ["ref", "Block.Color"], ["ref", "Is.RoadRestrictedArea"], ["ref", "RestrictedRoad.Color"], ["ref", "Is.Steps"], ["ref", "Steps.Color"], ["ref", "Is.PavedArea"], ["ref", "PavedArea.Color"], ["ref", "Is.Sand"], ["ref", "Sand.Color"], ["ref", "Is.UndergroundCity"], ["ref", "UndergroundArea.Color"], ["ref", "Is.Divider"], ["ref", "Divider.Color"], ["ref", "Is.PlaceOfWorship"], ["ref", "WorshipPlace.Color"], ["ref", "Is.School"], ["ref", "School.Color"], ["ref", "Is.Wetland"], ["ref", "Wetland.Color"], ["ref", "Is.Breakwater"], ["ref", "WaterBreak.Color"], ["ref", "Is.AccommodationFacility"], ["ref", "AccomodationFacility.Color"], ["ref", "Is.Attraction.Park"], ["ref", "Attraction.Color"], ["ref", "Is.Dam"], ["ref", "Dam.Color"], ["ref", "Is.ImperialFacility"], ["ref", "ImperialFacility.Color"], ["ref", "Is.InstitutionalOffice"], ["ref", "InstitutionalOffice.Color"], ["ref", "Is.OutdoorFacility"], ["ref", "OutdoorFacility.Color"], ["ref", "Is.Pool"], ["ref", "Pool.Color"], ["ref", "Is.Retail"], ["ref", "Retail.Color"], ["ref", "Is.ServiceArea"], ["ref", "ServiceArea.Color"], ["ref", "Is.Transportation"], ["ref", "Transportation.Color"], ["ref", "Is.TunnelEntrance"], ["ref", "TunnelEntrance.Color"], ["ref", "Is.RailwayStation"], ["ref", "RailwayStation.Color"], ["ref", "Is.CommuterStation"], ["ref", "CommuterStation.Color"], ["base-attribute-value"]]}}, {"id": "japan_landuse_lines", "styleSet": "tilezen_lines", "when": ["ref", "Is.JapanLanduseLines.Enabled"], "technique": "line", "description": "Landuse Lines", "minZoomLevel": ["case", ["ref", "Is.JapanLanduseLines.Enabled"], 15, null], "category": ["case", ["ref", "Is.TollGate"], "landuse_toll_gate", ["ref", "Is.DecorativeWaterRoute"], "ferry", ["ref", "Is.DecorativeStairs"], "landuse_stairs_lines", "landuse_lines"], "attr": {"smooth-steps": ["make-vector", 4, 0.75], "dasharray": ["case", ["ref", "Is.DecorativeWaterRoute"], ["ref", "Ferry.DashArray"], ["ref", "Is.TollGate"], ["ref", "TollGate.DashArray"], null], "fillcolor": ["case", ["ref", "Is.DecorativeWaterRoute"], ["ref", "Ferry.PolylineStyles.SecondaryColor"], "#00000000"], "color": ["case", ["ref", "Is.DecorativeLine"], ["ref", "DecorativeLine.Color"], ["ref", "Is.TollGate"], ["ref", "Divider.Color"], ["ref", "Is.FloodGate"], ["ref", "FloodGate.Color"], ["ref", "Is.DecorativeWaterRoute"], ["ref", "Ferry.PolylineStyles.Color"], ["ref", "Is.DecorativeStairs"], ["ref", "DecorativeStairs.Color"], ["ref", "Is.DecorativeDivider"], ["ref", "Divider.Color"], ["ref", "Is.DecorativeRoadLine"], ["ref", "DecorativeRoadLine.Color"], ["ref", "Is.DecorativeRailRoadLine"], ["ref", "DecorativeRailRoadLine.Color"], "#00000000"], "width": ["case", ["ref", "Is.DecorativeWaterRoute"], ["world-ppi-scale", ["ref", "Ferry.PolylineStyles.Width"]], ["ref", "Is.DecorativeExpressway"], ["world-ppi-scale", ["ref", "DecorativeExpresswayLine.Width"]], ["world-ppi-scale", ["ref", "DecorativeLines.Width"]]]}}]}