{"styles": [{"id": "japan_rail_labels", "extends": "rail_labels", "styleSet": "tilezen_lines", "when": ["==", ["get", "source"], "ipc"], "technique": "text", "category": ["case", ["ref", "Rail.Subway"], "japan-subway-rail-labels", ["ref", "Rail.Private"], "japan-private-rail-labels", ["ref", "Rail.State"], "japan-state-rail-labels", ["any", ["ref", "Rail.Tram"], ["ref", "Rail.Monorail"]], "japan-tram-rail-labels", ["ref", "Rail.Speed"], "japan-speed-rail-labels", ["ref", "CableCar"], "japan-cable-car-labels", ["ref", "Gondola"], "japan-gondola-labels", ["base-attribute-value"]], "attr": {"outline-size": ["case", ["ref", "Rail.Subway"], ["ppi-scale", ["ref", "SubwayRail.FontStyle.OutlineWidth"], ["ref", "ScalePpi.labels"]], ["ref", "Rail.State"], ["ppi-scale", ["ref", "StateRail.FontStyle.OutlineWidth"], ["ref", "ScalePpi.labels"]], ["ref", "Rail.Private"], ["ppi-scale", ["ref", "PrivateRail.FontStyle.OutlineWidth"], ["ref", "ScalePpi.labels"]], ["any", ["ref", "Rail.Tram"], ["ref", "Rail.Monorail"]], ["ppi-scale", ["ref", "TramRail.FontStyle.OutlineWidth"], ["ref", "ScalePpi.labels"]], ["ref", "Rail.Speed"], ["ppi-scale", ["ref", "SpeedRail.FontStyle.OutlineWidth"], ["ref", "ScalePpi.labels"]], ["ref", "CableCar"], ["ppi-scale", ["ref", "CableCar.FontStyle.OutlineWidth"], ["ref", "ScalePpi.labels"]], ["ref", "Gondola"], ["ppi-scale", ["ref", "Gondola.FontStyle.OutlineWidth"], ["ref", "ScalePpi.labels"]], ["base-attribute-value"]], "outline-color": ["case", ["ref", "Rail.Subway"], ["ref", "SubwayRail.FontStyle.OutlineColor"], ["ref", "Rail.Private"], ["ref", "PrivateRail.FontStyle.OutlineColor"], ["ref", "Rail.State"], ["ref", "StateRail.FontStyle.OutlineColor"], ["any", ["ref", "Rail.Tram"], ["ref", "Rail.Monorail"]], ["ref", "TramRail.FontStyle.OutlineColor"], ["ref", "Rail.Speed"], ["ref", "SpeedRail.FontStyle.OutlineColor"], ["ref", "CableCar"], ["ref", "CableCar.FontStyle.OutlineColor"], ["ref", "Gondola"], ["ref", "Gondola.FontStyle.OutlineColor"], ["base-attribute-value"]], "color": ["case", ["ref", "Rail.Subway"], ["ref", "SubwayRail.FontStyle.Color"], ["ref", "Rail.Private"], ["ref", "PrivateRail.FontStyle.Color"], ["ref", "Rail.State"], ["ref", "StateRail.FontStyle.Color"], ["any", ["ref", "Rail.Tram"], ["ref", "Rail.Monorail"]], ["ref", "TramRail.FontStyle.Color"], ["ref", "Rail.Speed"], ["ref", "SpeedRail.FontStyle.Color"], ["ref", "CableCar"], ["ref", "CableCar.FontStyle.Color"], ["ref", "Gondola"], ["ref", "Gondola.FontStyle.Color"], ["base-attribute-value"]], "size": ["case", ["ref", "Rail.Subway"], ["ppi-scale", ["ref", "SubwayRail.FontStyle.Size"], ["ref", "ScalePpi.labels"]], ["ref", "Rail.State"], ["ppi-scale", ["ref", "StateRail.FontStyle.Size"], ["ref", "ScalePpi.labels"]], ["ref", "Rail.Private"], ["ppi-scale", ["ref", "PrivateRail.FontStyle.Size"], ["ref", "ScalePpi.labels"]], ["any", ["ref", "Rail.Tram"], ["ref", "Rail.Monorail"]], ["ppi-scale", ["ref", "TramRail.FontStyle.Size"], ["ref", "ScalePpi.labels"]], ["ref", "Rail.Speed"], ["ppi-scale", ["ref", "SpeedRail.FontStyle.Size"], ["ref", "ScalePpi.labels"]], ["ref", "CableCar"], ["ppi-scale", ["ref", "CableCar.FontStyle.Size"], ["ref", "ScalePpi.labels"]], ["ref", "Gondola"], ["ppi-scale", ["ref", "Gondola.FontStyle.Size"], ["ref", "ScalePpi.labels"]], ["base-attribute-value"]]}}, {"id": "japan_rail_outlines", "extends": "rail_outlines", "styleSet": "tilezen_lines", "when": ["==", ["get", "source"], "ipc"], "technique": "line", "category": ["case", ["ref", "Rail.State"], "japan-state-rail-outline", ["ref", "Rail.Speed"], "japan-speed-rail-outline", ["ref", "Is.Railroad"], "japan-rail-outline", ["ref", "Rail.Subway"], "japan-subway-rail-outline", ["ref", "Rail.Private"], "japan-private-rail-outline", ["any", ["ref", "Rail.Tram"], ["ref", "Rail.Monorail"]], "japan-tram-rail-outline", ["ref", "CableCar"], "japan-cable-car-outline", ["ref", "Gondola"], "japan-gondola-outline", ["base-attribute-value"]], "maxZoomLevel": ["ref", "Rail.MaxZoomLevel"], "attr": {"opacity": ["ref", "Rail.Opacity"], "width": ["case", ["ref", "Rail.State"], ["world-ppi-scale", ["ref", "StateRail.PolylineStyles.OutlineWidth"]], ["ref", "Rail.Speed"], ["world-ppi-scale", ["ref", "SpeedRail.PolylineStyles.OutlineWidth"]], ["ref", "Rail.Subway"], ["world-ppi-scale", ["ref", "SubwayRail.PolylineStyles.OutlineWidth"]], ["ref", "Rail.Private"], ["world-ppi-scale", ["ref", "PrivateRail.PolylineStyles.OutlineWidth"]], ["any", ["ref", "Rail.Tram"], ["ref", "Rail.Monorail"]], ["world-ppi-scale", ["ref", "TramRail.PolylineStyles.OutlineWidth"]], ["ref", "CableCar"], ["world-ppi-scale", ["ref", "CableCar.OutlineWidth"]], ["ref", "Gondola"], ["world-ppi-scale", ["ref", "Gondola.OutlineWidth"]], ["base-attribute-value"]], "color": ["case", ["ref", "Rail.State"], ["ref", "StateRail.PolylineStyles.OutlineColor"], ["ref", "Rail.Speed"], ["ref", "SpeedRail.PolylineStyles.OutlineColor"], ["ref", "Rail.Subway"], ["ref", "SubwayRail.PolylineStyles.OutlineColor"], ["ref", "Rail.Private"], ["ref", "PrivateRail.PolylineStyles.OutlineColor"], ["any", ["ref", "Rail.Tram"], ["ref", "Rail.Monorail"]], ["ref", "TramRail.PolylineStyles.OutlineColor"], ["ref", "CableCar"], ["ref", "CableCar.OutlineColor"], ["ref", "Gondola"], ["ref", "Gondola.OutlineColor"], ["base-attribute-value"]], "smooth-steps": ["make-vector", 4, 0.75]}}, {"id": "japan_rail_lines", "extends": "rail_lines", "styleSet": "tilezen_lines", "when": ["==", ["get", "source"], "ipc"], "technique": "line", "category": ["case", ["ref", "Rail.Private"], "japan-private-rail", ["ref", "Rail.State"], "japan-state-rail", ["ref", "Rail.Subway"], "japan-subway-rail", ["any", ["ref", "Rail.Tram"], ["ref", "Rail.Monorail"]], "japan-tram-rail", ["ref", "Rail.Speed"], "japan-speed-rail", ["ref", "Is.Railroad"], "japan-rail", ["ref", "CableCar"], "japan-cable-car", ["ref", "Gondola"], "japan-gondola", ["base-attribute-value"]], "maxZoomLevel": ["ref", "Rail.MaxZoomLevel"], "attr": {"opacity": ["ref", "Rail.Opacity"], "dasharray": ["case", ["ref", "Rail.State"], ["make-vector", ["world-discrete-ppi-scale", ["ref", "StateRail.PolylineStyles.DashArray1"]], ["world-discrete-ppi-scale", ["ref", "StateRail.PolylineStyles.DashArray2"]], 0, 0], ["ref", "Rail.Speed"], ["make-vector", ["world-discrete-ppi-scale", ["ref", "SpeedRail.PolylineStyles.DashArray1"]], ["world-discrete-ppi-scale", ["ref", "SpeedRail.PolylineStyles.DashArray2"]], 0, 0], null], "fillcolor": ["case", ["ref", "Rail.State"], ["ref", "StateRail.PolylineStyles.SecondaryColor"], ["ref", "Rail.Speed"], ["ref", "SpeedRail.PolylineStyles.SecondaryColor"], ["base-attribute-value"]], "width": ["case", ["ref", "Rail.Private"], ["world-ppi-scale", ["ref", "PrivateRail.PolylineStyles.Width"]], ["ref", "Rail.State"], ["world-ppi-scale", ["ref", "StateRail.PolylineStyles.Width"]], ["ref", "Rail.Speed"], ["world-ppi-scale", ["ref", "SpeedRail.PolylineStyles.Width"]], ["any", ["ref", "Rail.Tram"], ["ref", "Rail.Monorail"]], ["world-ppi-scale", ["ref", "TramRail.PolylineStyles.Width"]], ["ref", "Rail.Subway"], ["world-ppi-scale", ["ref", "SubwayRail.PolylineStyles.Width"]], ["ref", "CableCar"], ["world-ppi-scale", ["ref", "CableCar.Width"]], ["ref", "Gondola"], ["world-ppi-scale", ["ref", "Gondola.Width"]], ["base-attribute-value"]], "color": ["case", ["ref", "Rail.Private"], ["ref", "PrivateRail.PolylineStyles.Color"], ["ref", "Rail.State"], ["ref", "StateRail.PolylineStyles.Color"], ["ref", "Rail.Speed"], ["ref", "SpeedRail.PolylineStyles.Color"], ["any", ["ref", "Rail.Tram"], ["ref", "Rail.Monorail"]], ["ref", "TramRail.PolylineStyles.Color"], ["ref", "Rail.Subway"], ["ref", "SubwayRail.PolylineStyles.Color"], ["ref", "CableCar"], ["ref", "CableCar.Color"], ["ref", "Gondola"], ["ref", "Gondola.Color"], ["base-attribute-value"]], "smooth-steps": ["case", ["any", ["ref", "CableCar"], ["ref", "Gondola"]], ["make-vector", 4, 2], ["make-vector", 4, 0.75]]}}]}